currencyApi/__init__.py
currency_api_py-0.1.0.dist-info/LICENSE
currency_api_py-0.1.0.dist-info/METADATA
currency_api_py-0.1.0.dist-info/WHEEL
currency_api_py-0.1.0.dist-info/top_level.txt
currency_api_py-0.1.0.dist-info/RECORD
