Metadata-Version: 2.1
Name: currency-api-py
Version: 0.1.0
Summary: A python async wrapper for the currency-api API
Home-page: https://github.com/Marseel-E/currency-api-py
Author: Marseel Eeso
Author-email: marseeleeso@gmail.com
License: UNKNOWN
Project-URL: Bug Tracker, https://github.com/Marseel-E/currency-api-py/issues
Platform: UNKNOWN
Classifier: Programming Language :: Python :: 3
Classifier: License :: OSI Approved :: MIT License
Classifier: Operating System :: OS Independent
Requires-Python: >=3.8
License-File: LICENSE
